CHANGELOG.md
bootloader/__init__.py
bootloader/scooby/__init__.py
bootloader/scooby/constant/__init__.py
bootloader/scooby/constant/asset.py
bootloader/scooby/constant/sort_order.py
bootloader/scooby/constant/ue_asset.py
bootloader/scooby/constant/unity_asset.py
bootloader/scooby/model/__init__.py
bootloader/scooby/model/asset.py
bootloader/scooby/model/l10n.py
bootloader/scooby/model/ue_asset.py
bootloader/scooby/model/unity_asset.py
bootloader_core_library-0.0.37.dist-info/LICENSE.md
bootloader_core_library-0.0.37.dist-info/WHEEL
bootloader_core_library-0.0.37.dist-info/METADATA
bootloader_core_library-0.0.37.dist-info/RECORD
