Metadata-Version: 2.1
Name: bootloader-core-library
Version: 0.0.37
Summary: Repository of reusable Python components to be shared by Python projects using the Bootloader services
Home-page: https://github.com/bootloader-studio/bootloader-core-python-library
License: SEE LICENSE IN <LICENSE.md>
Keywords: core,library
Author: Daniel CAUNE
Author-email: daniel@bootloader.studio
Requires-Python: >=3.10,<4.0
Classifier: Development Status :: 5 - Production/Stable
Classifier: License :: Other/Proprietary License
Classifier: Operating System :: OS Independent
Classifier: Programming Language :: Python
Classifier: Programming Language :: Python :: 3
Classifier: Programming Language :: Python :: 3.10
Classifier: Programming Language :: Python :: 3.11
Classifier: Topic :: Software Development :: Libraries
Requires-Dist: perseus-core-library (>=1.19,<2.0)
Project-URL: Repository, https://github.com/bootloader-studio/bootloader-core-python-library
